mhmpy/__init__.py
mhmpy/_version.py
mhmpy-0.0.0.dist-info/LICENSE
mhmpy-0.0.0.dist-info/METADATA
mhmpy-0.0.0.dist-info/WHEEL
mhmpy-0.0.0.dist-info/top_level.txt
mhmpy-0.0.0.dist-info/RECORD
